packstack/__init__.py
packstack/version.py
packstack/installer/LICENSE
packstack/installer/__init__.py
packstack/installer/basedefs.py
packstack/installer/exceptions.py
packstack/installer/output_messages.py
packstack/installer/processors.py
packstack/installer/run_setup.py
packstack/installer/setup_controller.py
packstack/installer/validators.py
packstack/installer/core/__init__.py
packstack/installer/core/arch.py
packstack/installer/core/drones.py
packstack/installer/core/parameters.py
packstack/installer/core/sequences.py
packstack/installer/utils/__init__.py
packstack/installer/utils/datastructures.py
packstack/installer/utils/decorators.py
packstack/installer/utils/network.py
packstack/installer/utils/shell.py
packstack/installer/utils/shortcuts.py
packstack/installer/utils/strings.py
packstack/modules/__init__.py
packstack/modules/common.py
packstack/modules/documentation.py
packstack/modules/ospluginutils.py
packstack/modules/puppet.py
packstack/plugins/__init__.py
packstack/plugins/amqp_002.py
packstack/plugins/aodh_810.py
packstack/plugins/ceilometer_800.py
packstack/plugins/cinder_250.py
packstack/plugins/dashboard_500.py
packstack/plugins/glance_200.py
packstack/plugins/gnocchi_790.py
packstack/plugins/heat_650.py
packstack/plugins/ironic_275.py
packstack/plugins/keystone_100.py
packstack/plugins/magnum_920.py
packstack/plugins/manila_355.py
packstack/plugins/mariadb_003.py
packstack/plugins/neutron_350.py
packstack/plugins/nova_300.py
packstack/plugins/openstack_client_400.py
packstack/plugins/postscript_951.py
packstack/plugins/prescript_000.py
packstack/plugins/provision_700.py
packstack/plugins/puppet_950.py
packstack/plugins/ssl_001.py
packstack/plugins/swift_600.py
packstack/plugins/trove_850.py
packstack/puppet/modules/packstack/Gemfile
packstack/puppet/modules/packstack/Rakefile
packstack/puppet/modules/packstack/lib/facter/default_hypervisor.rb
packstack/puppet/modules/packstack/lib/facter/home_dir.rb
packstack-26.0.0.dist-info/AUTHORS
packstack-26.0.0.dist-info/LICENSE
packstack-26.0.0.dist-info/METADATA
packstack-26.0.0.dist-info/WHEEL
packstack-26.0.0.dist-info/entry_points.txt
packstack-26.0.0.dist-info/pbr.json
packstack-26.0.0.dist-info/top_level.txt
packstack-26.0.0.dist-info/RECORD
