Metadata-Version: 2.1
Name: packstack
Version: 26.0.0
Summary: A utility to install OpenStack
Home-page: http://www.rdoproject.org/
Author: RDO
Author-email: rdo-list@redhat.com
Classifier: Environment :: OpenStack
Classifier: Intended Audience :: Developers
Classifier: Intended Audience :: Information Technology
Classifier: Intended Audience :: System Administrators
Classifier: License :: OSI Approved :: Apache Software License
Classifier: Operating System :: POSIX :: Linux
Classifier: Programming Language :: Python
Classifier: Programming Language :: Python :: 3.6
Classifier: Programming Language :: Python :: 3.9
Requires-Python: >=3.6
License-File: LICENSE
License-File: AUTHORS
Requires-Dist: pbr >=1.6
Requires-Dist: netaddr >=0.7.6
Requires-Dist: PyYAML >=3.10
Requires-Dist: docutils >=0.11
Requires-Dist: netifaces
Requires-Dist: distro
Requires-Dist: cryptography >=2.1
